fastapiauth/__init__.py
fastapiauth/fast_api_auth.py
fastapiauth-1.0.0.dist-info/LICENSE
fastapiauth-1.0.0.dist-info/METADATA
fastapiauth-1.0.0.dist-info/WHEEL
fastapiauth-1.0.0.dist-info/top_level.txt
fastapiauth-1.0.0.dist-info/RECORD
