Metadata-Version: 2.1
Name: fastapiauth
Version: 1.0.0
Summary: JWT auth for your fast api
Home-page: UNKNOWN
Author: Korhenon
Author-email: korhenon.code@gmail.com
License: UNKNOWN
Platform: UNKNOWN
Requires-Python: >=3.6
Requires-Dist: PyJWT
Requires-Dist: pydantic
Requires-Dist: fastapi
